openioe/__init__.py
openioe/myfile.py
openioe/openioe_apis.py
openioe-1.1.1.data/scripts/openioe_apis.py
openioe-1.1.1.dist-info/LICENSE
openioe-1.1.1.dist-info/METADATA
openioe-1.1.1.dist-info/WHEEL
openioe-1.1.1.dist-info/top_level.txt
openioe-1.1.1.dist-info/RECORD
