Metadata-Version: 2.1
Name: openioe
Version: 1.1.1
Summary: Open IoE
Home-page: https://openioe.in/
Author: Dr Venkataswamy R
Author-email: opensourceioe@gmail.com
Classifier: Programming Language :: Python :: 3
Classifier: License :: OSI Approved :: MIT License
Classifier: Operating System :: OS Independent
Requires-Python: >=3.6
License-File: LICENSE
